{
  "video": "videos/liamb30.MP4",
  "frames": [
    {
      "frame_idx": 52,
      "timestamp": 0.8671,
      "right_knee_angle": 155.31,
      "left_knee_angle": 101.47,
      "right_hip_angle": 131.71,
      "left_hip_angle": 108.16
    },
    {
      "frame_idx": 53,
      "timestamp": 0.8838,
      "right_knee_angle": 123.37,
      "left_knee_angle": 97.78,
      "right_hip_angle": 103.3,
      "left_hip_angle": 101.33
    },
    {
      "frame_idx": 54,
      "timestamp": 0.9005,
      "right_knee_angle": null,
      "left_knee_angle": 101.8,
      "right_hip_angle": 104.23,
      "left_hip_angle": 103.07
    },
    {
      "frame_idx": 55,
      "timestamp": 0.9172,
      "right_knee_angle": 126.33,
      "left_knee_angle": 105.22,
      "right_hip_angle": 103.79,
      "left_hip_angle": 103.61
    },
    {
      "frame_idx": 56,
      "timestamp": 0.9338,
      "right_knee_angle": 117.38,
      "left_knee_angle": 100.46,
      "right_hip_angle": 98.79,
      "left_hip_angle": 99.9
    },
    {
      "frame_idx": 57,
      "timestamp": 0.9505,
      "right_knee_angle": 117.64,
      "left_knee_angle": 101.61,
      "right_hip_angle": 104.81,
      "left_hip_angle": 101.49
    },
    {
      "frame_idx": 58,
      "timestamp": 0.9672,
      "right_knee_angle": 119.81,
      "left_knee_angle": 104.25,
      "right_hip_angle": 107.94,
      "left_hip_angle": 103.06
    },
    {
      "frame_idx": 59,
      "timestamp": 0.9839,
      "right_knee_angle": 113.98,
      "left_knee_angle": 102.45,
      "right_hip_angle": 104.46,
      "left_hip_angle": 99.92
    },
    {
      "frame_idx": 60,
      "timestamp": 1.0005,
      "right_knee_angle": null,
      "left_knee_angle": 103.73,
      "right_hip_angle": 100.1,
      "left_hip_angle": 103.47
    },
    {
      "frame_idx": 61,
      "timestamp": 1.0172,
      "right_knee_angle": null,
      "left_knee_angle": 107.73,
      "right_hip_angle": 95.91,
      "left_hip_angle": 107.29
    },
    {
      "frame_idx": 62,
      "timestamp": 1.0339,
      "right_knee_angle": 102.55,
      "left_knee_angle": 111.47,
      "right_hip_angle": 102.35,
      "left_hip_angle": 107.64
    },
    {
      "frame_idx": 63,
      "timestamp": 1.0506,
      "right_knee_angle": 107.62,
      "left_knee_angle": 117.14,
      "right_hip_angle": 113.53,
      "left_hip_angle": 108.93
    },
    {
      "frame_idx": 64,
      "timestamp": 1.0672,
      "right_knee_angle": 105.48,
      "left_knee_angle": 118.61,
      "right_hip_angle": 119.08,
      "left_hip_angle": 113.48
    },
    {
      "frame_idx": 65,
      "timestamp": 1.0839,
      "right_knee_angle": 96.27,
      "left_knee_angle": 121.54,
      "right_hip_angle": 114.85,
      "left_hip_angle": 116.1
    },
    {
      "frame_idx": 66,
      "timestamp": 1.1006,
      "right_knee_angle": 93.16,
      "left_knee_angle": 126.05,
      "right_hip_angle": 111.63,
      "left_hip_angle": 115.17
    },
    {
      "frame_idx": 67,
      "timestamp": 1.1173,
      "right_knee_angle": 92.29,
      "left_knee_angle": 132.8,
      "right_hip_angle": 111.69,
      "left_hip_angle": 120.39
    },
    {
      "frame_idx": 68,
      "timestamp": 1.1339,
      "right_knee_angle": 89.83,
      "left_knee_angle": 134.4,
      "right_hip_angle": 107.05,
      "left_hip_angle": 119.28
    },
    {
      "frame_idx": 69,
      "timestamp": 1.1506,
      "right_knee_angle": 87.61,
      "left_knee_angle": 139.36,
      "right_hip_angle": 107.03,
      "left_hip_angle": 122.47
    },
    {
      "frame_idx": 70,
      "timestamp": 1.1673,
      "right_knee_angle": 89.37,
      "left_knee_angle": 142.25,
      "right_hip_angle": 105.98,
      "left_hip_angle": 122.31
    },
    {
      "frame_idx": 71,
      "timestamp": 1.184,
      "right_knee_angle": 85.52,
      "left_knee_angle": 144.35,
      "right_hip_angle": 103.67,
      "left_hip_angle": 124.64
    },
    {
      "frame_idx": 72,
      "timestamp": 1.2006,
      "right_knee_angle": 84.08,
      "left_knee_angle": 142.6,
      "right_hip_angle": 102.9,
      "left_hip_angle": 122.39
    },
    {
      "frame_idx": 73,
      "timestamp": 1.2173,
      "right_knee_angle": 83.34,
      "left_knee_angle": 143.14,
      "right_hip_angle": 98.55,
      "left_hip_angle": 122.38
    },
    {
      "frame_idx": 74,
      "timestamp": 1.234,
      "right_knee_angle": 87.42,
      "left_knee_angle": 144.66,
      "right_hip_angle": 99.51,
      "left_hip_angle": 124.53
    },
    {
      "frame_idx": 75,
      "timestamp": 1.2507,
      "right_knee_angle": 96.58,
      "left_knee_angle": 143.87,
      "right_hip_angle": 102.25,
      "left_hip_angle": 127.09
    },
    {
      "frame_idx": 76,
      "timestamp": 1.2674,
      "right_knee_angle": 94.69,
      "left_knee_angle": 141.17,
      "right_hip_angle": 98.12,
      "left_hip_angle": 124.78
    },
    {
      "frame_idx": 77,
      "timestamp": 1.284,
      "right_knee_angle": 87.76,
      "left_knee_angle": 136.61,
      "right_hip_angle": 91.65,
      "left_hip_angle": 123.19
    },
    {
      "frame_idx": 78,
      "timestamp": 1.3007,
      "right_knee_angle": 84.99,
      "left_knee_angle": 133.17,
      "right_hip_angle": 88.64,
      "left_hip_angle": 123.08
    },
    {
      "frame_idx": 79,
      "timestamp": 1.3174,
      "right_knee_angle": 88.83,
      "left_knee_angle": 128.9,
      "right_hip_angle": 90.77,
      "left_hip_angle": 120.04
    },
    {
      "frame_idx": 80,
      "timestamp": 1.3341,
      "right_knee_angle": 94.45,
      "left_knee_angle": 120.61,
      "right_hip_angle": 98.46,
      "left_hip_angle": 114.99
    },
    {
      "frame_idx": 81,
      "timestamp": 1.3507,
      "right_knee_angle": 92.65,
      "left_knee_angle": 116.23,
      "right_hip_angle": 91.92,
      "left_hip_angle": 112.54
    },
    {
      "frame_idx": 82,
      "timestamp": 1.3674,
      "right_knee_angle": 96.4,
      "left_knee_angle": 114.62,
      "right_hip_angle": 95.53,
      "left_hip_angle": 112.61
    },
    {
      "frame_idx": 83,
      "timestamp": 1.3841,
      "right_knee_angle": 96.9,
      "left_knee_angle": 107.14,
      "right_hip_angle": 93.1,
      "left_hip_angle": 109.25
    },
    {
      "frame_idx": 84,
      "timestamp": 1.4008,
      "right_knee_angle": 102.8,
      "left_knee_angle": 102.36,
      "right_hip_angle": 99.22,
      "left_hip_angle": 108.3
    },
    {
      "frame_idx": 85,
      "timestamp": 1.4174,
      "right_knee_angle": 105.28,
      "left_knee_angle": 101.55,
      "right_hip_angle": 99.62,
      "left_hip_angle": 107.34
    },
    {
      "frame_idx": 86,
      "timestamp": 1.4341,
      "right_knee_angle": 112.13,
      "left_knee_angle": 98.05,
      "right_hip_angle": 111.17,
      "left_hip_angle": 105.99
    },
    {
      "frame_idx": 87,
      "timestamp": 1.4508,
      "right_knee_angle": 115.83,
      "left_knee_angle": 93.48,
      "right_hip_angle": 111.05,
      "left_hip_angle": 103.6
    },
    {
      "frame_idx": 88,
      "timestamp": 1.4675,
      "right_knee_angle": 117.63,
      "left_knee_angle": 90.58,
      "right_hip_angle": 112.35,
      "left_hip_angle": 105.41
    },
    {
      "frame_idx": 89,
      "timestamp": 1.4841,
      "right_knee_angle": 122.19,
      "left_knee_angle": 90.43,
      "right_hip_angle": 115.74,
      "left_hip_angle": 98.19
    },
    {
      "frame_idx": 90,
      "timestamp": 1.5008,
      "right_knee_angle": 130.64,
      "left_knee_angle": 84.82,
      "right_hip_angle": 112.46,
      "left_hip_angle": 96.52
    },
    {
      "frame_idx": 91,
      "timestamp": 1.5175,
      "right_knee_angle": 129.87,
      "left_knee_angle": 85.28,
      "right_hip_angle": 115.25,
      "left_hip_angle": 96.15
    },
    {
      "frame_idx": 343,
      "timestamp": 5.7198,
      "right_knee_angle": null,
      "left_knee_angle": 82.87,
      "right_hip_angle": 80.97,
      "left_hip_angle": 85.09
    },
    {
      "frame_idx": 344,
      "timestamp": 5.7364,
      "right_knee_angle": null,
      "left_knee_angle": null,
      "right_hip_angle": null,
      "left_hip_angle": null
    },
    {
      "frame_idx": 345,
      "timestamp": 5.7531,
      "right_knee_angle": null,
      "left_knee_angle": null,
      "right_hip_angle": null,
      "left_hip_angle": null
    },
    {
      "frame_idx": 346,
      "timestamp": 5.7698,
      "right_knee_angle": null,
      "left_knee_angle": null,
      "right_hip_angle": null,
      "left_hip_angle": null
    },
    {
      "frame_idx": 347,
      "timestamp": 5.7865,
      "right_knee_angle": null,
      "left_knee_angle": null,
      "right_hip_angle": null,
      "left_hip_angle": null
    },
    {
      "frame_idx": 348,
      "timestamp": 5.8031,
      "right_knee_angle": null,
      "left_knee_angle": null,
      "right_hip_angle": null,
      "left_hip_angle": null
    },
    {
      "frame_idx": 349,
      "timestamp": 5.8198,
      "right_knee_angle": null,
      "left_knee_angle": null,
      "right_hip_angle": null,
      "left_hip_angle": null
    },
    {
      "frame_idx": 350,
      "timestamp": 5.8365,
      "right_knee_angle": null,
      "left_knee_angle": null,
      "right_hip_angle": null,
      "left_hip_angle": null
    },
    {
      "frame_idx": 351,
      "timestamp": 5.8532,
      "right_knee_angle": null,
      "left_knee_angle": null,
      "right_hip_angle": null,
      "left_hip_angle": null
    },
    {
      "frame_idx": 352,
      "timestamp": 5.8698,
      "right_knee_angle": null,
      "left_knee_angle": null,
      "right_hip_angle": null,
      "left_hip_angle": null
    },
    {
      "frame_idx": 353,
      "timestamp": 5.8865,
      "right_knee_angle": null,
      "left_knee_angle": null,
      "right_hip_angle": null,
      "left_hip_angle": null
    },
    {
      "frame_idx": 354,
      "timestamp": 5.9032,
      "right_knee_angle": null,
      "left_knee_angle": null,
      "right_hip_angle": null,
      "left_hip_angle": null
    },
    {
      "frame_idx": 355,
      "timestamp": 5.9199,
      "right_knee_angle": 100.49,
      "left_knee_angle": 136.43,
      "right_hip_angle": 119.19,
      "left_hip_angle": 145.91
    },
    {
      "frame_idx": 356,
      "timestamp": 5.9365,
      "right_knee_angle": 142.89,
      "left_knee_angle": null,
      "right_hip_angle": 125.13,
      "left_hip_angle": null
    },
    {
      "frame_idx": 357,
      "timestamp": 5.9532,
      "right_knee_angle": 149.89,
      "left_knee_angle": 141.34,
      "right_hip_angle": 138.88,
      "left_hip_angle": 138.04
    },
    {
      "frame_idx": 358,
      "timestamp": 5.9699,
      "right_knee_angle": 142.1,
      "left_knee_angle": null,
      "right_hip_angle": 115.22,
      "left_hip_angle": null
    },
    {
      "frame_idx": 359,
      "timestamp": 5.9866,
      "right_knee_angle": 151.8,
      "left_knee_angle": 129.26,
      "right_hip_angle": 125.45,
      "left_hip_angle": 119.6
    },
    {
      "frame_idx": 360,
      "timestamp": 6.0032,
      "right_knee_angle": 146.43,
      "left_knee_angle": 169.46,
      "right_hip_angle": null,
      "left_hip_angle": null
    },
    {
      "frame_idx": 361,
      "timestamp": 6.0199,
      "right_knee_angle": 142.16,
      "left_knee_angle": 150.07,
      "right_hip_angle": 122.84,
      "left_hip_angle": 118.28
    },
    {
      "frame_idx": 362,
      "timestamp": 6.0366,
      "right_knee_angle": 143.72,
      "left_knee_angle": null,
      "right_hip_angle": null,
      "left_hip_angle": null
    },
    {
      "frame_idx": 363,
      "timestamp": 6.0533,
      "right_knee_angle": null,
      "left_knee_angle": null,
      "right_hip_angle": null,
      "left_hip_angle": null
    },
    {
      "frame_idx": 364,
      "timestamp": 6.0699,
      "right_knee_angle": null,
      "left_knee_angle": null,
      "right_hip_angle": null,
      "left_hip_angle": null
    },
    {
      "frame_idx": 365,
      "timestamp": 6.0866,
      "right_knee_angle": 130.02,
      "left_knee_angle": null,
      "right_hip_angle": 160.43,
      "left_hip_angle": null
    },
    {
      "frame_idx": 366,
      "timestamp": 6.1033,
      "right_knee_angle": 124.08,
      "left_knee_angle": null,
      "right_hip_angle": 122.17,
      "left_hip_angle": 114.38
    },
    {
      "frame_idx": 367,
      "timestamp": 6.12,
      "right_knee_angle": null,
      "left_knee_angle": null,
      "right_hip_angle": null,
      "left_hip_angle": null
    },
    {
      "frame_idx": 368,
      "timestamp": 6.1367,
      "right_knee_angle": 110.71,
      "left_knee_angle": null,
      "right_hip_angle": 101.41,
      "left_hip_angle": null
    },
    {
      "frame_idx": 369,
      "timestamp": 6.1533,
      "right_knee_angle": 118.41,
      "left_knee_angle": null,
      "right_hip_angle": 110.44,
      "left_hip_angle": null
    },
    {
      "frame_idx": 370,
      "timestamp": 6.17,
      "right_knee_angle": null,
      "left_knee_angle": null,
      "right_hip_angle": null,
      "left_hip_angle": null
    },
    {
      "frame_idx": 371,
      "timestamp": 6.1867,
      "right_knee_angle": 120.4,
      "left_knee_angle": null,
      "right_hip_angle": 99.92,
      "left_hip_angle": null
    },
    {
      "frame_idx": 372,
      "timestamp": 6.2034,
      "right_knee_angle": null,
      "left_knee_angle": null,
      "right_hip_angle": null,
      "left_hip_angle": null
    },
    {
      "frame_idx": 373,
      "timestamp": 6.22,
      "right_knee_angle": null,
      "left_knee_angle": null,
      "right_hip_angle": null,
      "left_hip_angle": null
    },
    {
      "frame_idx": 374,
      "timestamp": 6.2367,
      "right_knee_angle": null,
      "left_knee_angle": null,
      "right_hip_angle": null,
      "left_hip_angle": null
    },
    {
      "frame_idx": 375,
      "timestamp": 6.2534,
      "right_knee_angle": null,
      "left_knee_angle": null,
      "right_hip_angle": null,
      "left_hip_angle": null
    },
    {
      "frame_idx": 376,
      "timestamp": 6.2701,
      "right_knee_angle": 99.7,
      "left_knee_angle": null,
      "right_hip_angle": 106.39,
      "left_hip_angle": null
    },
    {
      "frame_idx": 377,
      "timestamp": 6.2867,
      "right_knee_angle": null,
      "left_knee_angle": null,
      "right_hip_angle": null,
      "left_hip_angle": null
    },
    {
      "frame_idx": 378,
      "timestamp": 6.3034,
      "right_knee_angle": 164.09,
      "left_knee_angle": null,
      "right_hip_angle": null,
      "left_hip_angle": null
    },
    {
      "frame_idx": 379,
      "timestamp": 6.3201,
      "right_knee_angle": null,
      "left_knee_angle": null,
      "right_hip_angle": null,
      "left_hip_angle": null
    },
    {
      "frame_idx": 380,
      "timestamp": 6.3368,
      "right_knee_angle": null,
      "left_knee_angle": null,
      "right_hip_angle": null,
      "left_hip_angle": null
    },
    {
      "frame_idx": 381,
      "timestamp": 6.3534,
      "right_knee_angle": null,
      "left_knee_angle": null,
      "right_hip_angle": null,
      "left_hip_angle": null
    },
    {
      "frame_idx": 382,
      "timestamp": 6.3701,
      "right_knee_angle": 158.11,
      "left_knee_angle": null,
      "right_hip_angle": 155.37,
      "left_hip_angle": null
    },
    {
      "frame_idx": 383,
      "timestamp": 6.3868,
      "right_knee_angle": null,
      "left_knee_angle": null,
      "right_hip_angle": null,
      "left_hip_angle": null
    },
    {
      "frame_idx": 384,
      "timestamp": 6.4035,
      "right_knee_angle": null,
      "left_knee_angle": null,
      "right_hip_angle": null,
      "left_hip_angle": null
    },
    {
      "frame_idx": 385,
      "timestamp": 6.4201,
      "right_knee_angle": null,
      "left_knee_angle": null,
      "right_hip_angle": null,
      "left_hip_angle": null
    },
    {
      "frame_idx": 386,
      "timestamp": 6.4368,
      "right_knee_angle": null,
      "left_knee_angle": null,
      "right_hip_angle": null,
      "left_hip_angle": null
    },
    {
      "frame_idx": 387,
      "timestamp": 6.4535,
      "right_knee_angle": null,
      "left_knee_angle": null,
      "right_hip_angle": null,
      "left_hip_angle": null
    },
    {
      "frame_idx": 388,
      "timestamp": 6.4702,
      "right_knee_angle": null,
      "left_knee_angle": null,
      "right_hip_angle": null,
      "left_hip_angle": null
    },
    {
      "frame_idx": 389,
      "timestamp": 6.4868,
      "right_knee_angle": 92.45,
      "left_knee_angle": null,
      "right_hip_angle": 85.46,
      "left_hip_angle": null
    },
    {
      "frame_idx": 390,
      "timestamp": 6.5035,
      "right_knee_angle": null,
      "left_knee_angle": null,
      "right_hip_angle": null,
      "left_hip_angle": null
    },
    {
      "frame_idx": 391,
      "timestamp": 6.5202,
      "right_knee_angle": 94.38,
      "left_knee_angle": null,
      "right_hip_angle": 86.99,
      "left_hip_angle": null
    },
    {
      "frame_idx": 392,
      "timestamp": 6.5369,
      "right_knee_angle": null,
      "left_knee_angle": null,
      "right_hip_angle": null,
      "left_hip_angle": null
    },
    {
      "frame_idx": 393,
      "timestamp": 6.5535,
      "right_knee_angle": 102.66,
      "left_knee_angle": null,
      "right_hip_angle": 80.9,
      "left_hip_angle": null
    },
    {
      "frame_idx": 394,
      "timestamp": 6.5702,
      "right_knee_angle": 104.79,
      "left_knee_angle": 117.93,
      "right_hip_angle": 89.7,
      "left_hip_angle": 96.96
    },
    {
      "frame_idx": 395,
      "timestamp": 6.5869,
      "right_knee_angle": 111.73,
      "left_knee_angle": 119.26,
      "right_hip_angle": 86.76,
      "left_hip_angle": 100.12
    },
    {
      "frame_idx": 396,
      "timestamp": 6.6036,
      "right_knee_angle": null,
      "left_knee_angle": null,
      "right_hip_angle": 89.29,
      "left_hip_angle": null
    },
    {
      "frame_idx": 397,
      "timestamp": 6.6202,
      "right_knee_angle": null,
      "left_knee_angle": null,
      "right_hip_angle": 89.34,
      "left_hip_angle": 99.9
    },
    {
      "frame_idx": 398,
      "timestamp": 6.6369,
      "right_knee_angle": 123.58,
      "left_knee_angle": null,
      "right_hip_angle": 103.03,
      "left_hip_angle": null
    },
    {
      "frame_idx": 399,
      "timestamp": 6.6536,
      "right_knee_angle": 137.22,
      "left_knee_angle": 149.37,
      "right_hip_angle": 118.96,
      "left_hip_angle": 121.29
    },
    {
      "frame_idx": 400,
      "timestamp": 6.6703,
      "right_knee_angle": 135.45,
      "left_knee_angle": 151.03,
      "right_hip_angle": 110.46,
      "left_hip_angle": 127.12
    },
    {
      "frame_idx": 401,
      "timestamp": 6.6869,
      "right_knee_angle": 143.35,
      "left_knee_angle": 143.8,
      "right_hip_angle": 116.71,
      "left_hip_angle": 123.52
    },
    {
      "frame_idx": 402,
      "timestamp": 6.7036,
      "right_knee_angle": 140.59,
      "left_knee_angle": 108.84,
      "right_hip_angle": 118.58,
      "left_hip_angle": 81.88
    },
    {
      "frame_idx": 403,
      "timestamp": 6.7203,
      "right_knee_angle": null,
      "left_knee_angle": null,
      "right_hip_angle": 97.74,
      "left_hip_angle": null
    },
    {
      "frame_idx": 404,
      "timestamp": 6.737,
      "right_knee_angle": 150.12,
      "left_knee_angle": null,
      "right_hip_angle": 146.11,
      "left_hip_angle": 65.56
    },
    {
      "frame_idx": 405,
      "timestamp": 6.7537,
      "right_knee_angle": null,
      "left_knee_angle": null,
      "right_hip_angle": 71.29,
      "left_hip_angle": null
    },
    {
      "frame_idx": 406,
      "timestamp": 6.7703,
      "right_knee_angle": 140.83,
      "left_knee_angle": 102.54,
      "right_hip_angle": 126.16,
      "left_hip_angle": 72.94
    },
    {
      "frame_idx": 407,
      "timestamp": 6.787,
      "right_knee_angle": 142.31,
      "left_knee_angle": 164.76,
      "right_hip_angle": 130.05,
      "left_hip_angle": 150.22
    },
    {
      "frame_idx": 408,
      "timestamp": 6.8037,
      "right_knee_angle": 132.29,
      "left_knee_angle": null,
      "right_hip_angle": 120.25,
      "left_hip_angle": null
    },
    {
      "frame_idx": 409,
      "timestamp": 6.8204,
      "right_knee_angle": 120.7,
      "left_knee_angle": null,
      "right_hip_angle": 118.37,
      "left_hip_angle": null
    },
    {
      "frame_idx": 410,
      "timestamp": 6.837,
      "right_knee_angle": 125.41,
      "left_knee_angle": null,
      "right_hip_angle": 123.0,
      "left_hip_angle": 147.3
    },
    {
      "frame_idx": 411,
      "timestamp": 6.8537,
      "right_knee_angle": 117.11,
      "left_knee_angle": null,
      "right_hip_angle": 126.35,
      "left_hip_angle": 69.99
    },
    {
      "frame_idx": 412,
      "timestamp": 6.8704,
      "right_knee_angle": 102.25,
      "left_knee_angle": null,
      "right_hip_angle": 109.2,
      "left_hip_angle": 76.1
    },
    {
      "frame_idx": 413,
      "timestamp": 6.8871,
      "right_knee_angle": null,
      "left_knee_angle": null,
      "right_hip_angle": null,
      "left_hip_angle": null
    },
    {
      "frame_idx": 414,
      "timestamp": 6.9037,
      "right_knee_angle": 93.62,
      "left_knee_angle": null,
      "right_hip_angle": 106.82,
      "left_hip_angle": 75.15
    },
    {
      "frame_idx": 415,
      "timestamp": 6.9204,
      "right_knee_angle": 121.06,
      "left_knee_angle": null,
      "right_hip_angle": 119.88,
      "left_hip_angle": 81.52
    },
    {
      "frame_idx": 416,
      "timestamp": 6.9371,
      "right_knee_angle": null,
      "left_knee_angle": null,
      "right_hip_angle": null,
      "left_hip_angle": null
    },
    {
      "frame_idx": 417,
      "timestamp": 6.9538,
      "right_knee_angle": 77.68,
      "left_knee_angle": null,
      "right_hip_angle": 100.3,
      "left_hip_angle": null
    },
    {
      "frame_idx": 418,
      "timestamp": 6.9704,
      "right_knee_angle": 111.2,
      "left_knee_angle": null,
      "right_hip_angle": 94.58,
      "left_hip_angle": null
    },
    {
      "frame_idx": 419,
      "timestamp": 6.9871,
      "right_knee_angle": 114.13,
      "left_knee_angle": null,
      "right_hip_angle": 102.83,
      "left_hip_angle": null
    },
    {
      "frame_idx": 420,
      "timestamp": 7.0038,
      "right_knee_angle": 119.02,
      "left_knee_angle": null,
      "right_hip_angle": 102.65,
      "left_hip_angle": 107.8
    },
    {
      "frame_idx": 421,
      "timestamp": 7.0205,
      "right_knee_angle": 126.95,
      "left_knee_angle": null,
      "right_hip_angle": 101.34,
      "left_hip_angle": null
    },
    {
      "frame_idx": 422,
      "timestamp": 7.0371,
      "right_knee_angle": null,
      "left_knee_angle": null,
      "right_hip_angle": null,
      "left_hip_angle": null
    },
    {
      "frame_idx": 423,
      "timestamp": 7.0538,
      "right_knee_angle": 120.86,
      "left_knee_angle": null,
      "right_hip_angle": 102.24,
      "left_hip_angle": null
    },
    {
      "frame_idx": 424,
      "timestamp": 7.0705,
      "right_knee_angle": 128.14,
      "left_knee_angle": null,
      "right_hip_angle": 107.3,
      "left_hip_angle": null
    },
    {
      "frame_idx": 425,
      "timestamp": 7.0872,
      "right_knee_angle": null,
      "left_knee_angle": null,
      "right_hip_angle": null,
      "left_hip_angle": null
    },
    {
      "frame_idx": 426,
      "timestamp": 7.1038,
      "right_knee_angle": null,
      "left_knee_angle": null,
      "right_hip_angle": null,
      "left_hip_angle": null
    },
    {
      "frame_idx": 427,
      "timestamp": 7.1205,
      "right_knee_angle": null,
      "left_knee_angle": null,
      "right_hip_angle": null,
      "left_hip_angle": null
    },
    {
      "frame_idx": 428,
      "timestamp": 7.1372,
      "right_knee_angle": 114.13,
      "left_knee_angle": null,
      "right_hip_angle": 104.97,
      "left_hip_angle": null
    },
    {
      "frame_idx": 429,
      "timestamp": 7.1539,
      "right_knee_angle": 108.4,
      "left_knee_angle": null,
      "right_hip_angle": 109.19,
      "left_hip_angle": null
    },
    {
      "frame_idx": 430,
      "timestamp": 7.1705,
      "right_knee_angle": null,
      "left_knee_angle": null,
      "right_hip_angle": null,
      "left_hip_angle": null
    },
    {
      "frame_idx": 431,
      "timestamp": 7.1872,
      "right_knee_angle": 118.59,
      "left_knee_angle": null,
      "right_hip_angle": 97.66,
      "left_hip_angle": null
    },
    {
      "frame_idx": 432,
      "timestamp": 7.2039,
      "right_knee_angle": null,
      "left_knee_angle": null,
      "right_hip_angle": 101.43,
      "left_hip_angle": null
    },
    {
      "frame_idx": 433,
      "timestamp": 7.2206,
      "right_knee_angle": 108.72,
      "left_knee_angle": null,
      "right_hip_angle": 107.6,
      "left_hip_angle": null
    },
    {
      "frame_idx": 434,
      "timestamp": 7.2372,
      "right_knee_angle": 109.65,
      "left_knee_angle": 128.55,
      "right_hip_angle": 111.75,
      "left_hip_angle": 136.14
    },
    {
      "frame_idx": 435,
      "timestamp": 7.2539,
      "right_knee_angle": 104.4,
      "left_knee_angle": 104.92,
      "right_hip_angle": 97.86,
      "left_hip_angle": 108.25
    },
    {
      "frame_idx": 436,
      "timestamp": 7.2706,
      "right_knee_angle": 113.2,
      "left_knee_angle": null,
      "right_hip_angle": 99.13,
      "left_hip_angle": 97.44
    },
    {
      "frame_idx": 437,
      "timestamp": 7.2873,
      "right_knee_angle": 106.13,
      "left_knee_angle": 115.18,
      "right_hip_angle": 108.24,
      "left_hip_angle": 117.5
    },
    {
      "frame_idx": 438,
      "timestamp": 7.3039,
      "right_knee_angle": 107.73,
      "left_knee_angle": null,
      "right_hip_angle": 94.11,
      "left_hip_angle": 107.65
    },
    {
      "frame_idx": 439,
      "timestamp": 7.3206,
      "right_knee_angle": null,
      "left_knee_angle": null,
      "right_hip_angle": null,
      "left_hip_angle": null
    },
    {
      "frame_idx": 440,
      "timestamp": 7.3373,
      "right_knee_angle": 119.55,
      "left_knee_angle": null,
      "right_hip_angle": 107.37,
      "left_hip_angle": null
    },
    {
      "frame_idx": 441,
      "timestamp": 7.354,
      "right_knee_angle": 143.53,
      "left_knee_angle": 162.15,
      "right_hip_angle": 128.94,
      "left_hip_angle": 153.38
    },
    {
      "frame_idx": 442,
      "timestamp": 7.3707,
      "right_knee_angle": 139.57,
      "left_knee_angle": 172.05,
      "right_hip_angle": 126.62,
      "left_hip_angle": 163.58
    },
    {
      "frame_idx": 443,
      "timestamp": 7.3873,
      "right_knee_angle": 139.85,
      "left_knee_angle": 169.47,
      "right_hip_angle": 141.08,
      "left_hip_angle": 165.77
    },
    {
      "frame_idx": 444,
      "timestamp": 7.404,
      "right_knee_angle": 148.56,
      "left_knee_angle": null,
      "right_hip_angle": 147.3,
      "left_hip_angle": 92.08
    },
    {
      "frame_idx": 445,
      "timestamp": 7.4207,
      "right_knee_angle": 130.5,
      "left_knee_angle": null,
      "right_hip_angle": 137.36,
      "left_hip_angle": null
    },
    {
      "frame_idx": 446,
      "timestamp": 7.4374,
      "right_knee_angle": 134.43,
      "left_knee_angle": null,
      "right_hip_angle": 138.97,
      "left_hip_angle": 90.91
    },
    {
      "frame_idx": 447,
      "timestamp": 7.454,
      "right_knee_angle": 143.16,
      "left_knee_angle": 162.68,
      "right_hip_angle": 140.1,
      "left_hip_angle": 162.96
    },
    {
      "frame_idx": 448,
      "timestamp": 7.4707,
      "right_knee_angle": 129.7,
      "left_knee_angle": null,
      "right_hip_angle": 129.62,
      "left_hip_angle": null
    },
    {
      "frame_idx": 449,
      "timestamp": 7.4874,
      "right_knee_angle": 130.78,
      "left_knee_angle": null,
      "right_hip_angle": 134.26,
      "left_hip_angle": null
    },
    {
      "frame_idx": 450,
      "timestamp": 7.5041,
      "right_knee_angle": null,
      "left_knee_angle": null,
      "right_hip_angle": null,
      "left_hip_angle": null
    },
    {
      "frame_idx": 451,
      "timestamp": 7.5207,
      "right_knee_angle": null,
      "left_knee_angle": null,
      "right_hip_angle": null,
      "left_hip_angle": null
    },
    {
      "frame_idx": 452,
      "timestamp": 7.5374,
      "right_knee_angle": null,
      "left_knee_angle": null,
      "right_hip_angle": null,
      "left_hip_angle": null
    },
    {
      "frame_idx": 453,
      "timestamp": 7.5541,
      "right_knee_angle": 124.21,
      "left_knee_angle": null,
      "right_hip_angle": 126.64,
      "left_hip_angle": null
    },
    {
      "frame_idx": 454,
      "timestamp": 7.5708,
      "right_knee_angle": null,
      "left_knee_angle": null,
      "right_hip_angle": 146.93,
      "left_hip_angle": 90.51
    },
    {
      "frame_idx": 455,
      "timestamp": 7.5874,
      "right_knee_angle": 137.59,
      "left_knee_angle": null,
      "right_hip_angle": 156.82,
      "left_hip_angle": null
    },
    {
      "frame_idx": 456,
      "timestamp": 7.6041,
      "right_knee_angle": null,
      "left_knee_angle": null,
      "right_hip_angle": 116.72,
      "left_hip_angle": null
    },
    {
      "frame_idx": 457,
      "timestamp": 7.6208,
      "right_knee_angle": null,
      "left_knee_angle": null,
      "right_hip_angle": null,
      "left_hip_angle": 91.69
    },
    {
      "frame_idx": 458,
      "timestamp": 7.6375,
      "right_knee_angle": 117.81,
      "left_knee_angle": 109.1,
      "right_hip_angle": 112.45,
      "left_hip_angle": 114.68
    },
    {
      "frame_idx": 459,
      "timestamp": 7.6541,
      "right_knee_angle": 108.92,
      "left_knee_angle": null,
      "right_hip_angle": 103.58,
      "left_hip_angle": null
    },
    {
      "frame_idx": 460,
      "timestamp": 7.6708,
      "right_knee_angle": 100.95,
      "left_knee_angle": null,
      "right_hip_angle": 108.07,
      "left_hip_angle": 92.08
    },
    {
      "frame_idx": 461,
      "timestamp": 7.6875,
      "right_knee_angle": 123.51,
      "left_knee_angle": 158.2,
      "right_hip_angle": 104.42,
      "left_hip_angle": 148.26
    },
    {
      "frame_idx": 462,
      "timestamp": 7.7042,
      "right_knee_angle": 130.08,
      "left_knee_angle": 132.63,
      "right_hip_angle": 107.69,
      "left_hip_angle": 135.13
    },
    {
      "frame_idx": 463,
      "timestamp": 7.7208,
      "right_knee_angle": 90.78,
      "left_knee_angle": 82.01,
      "right_hip_angle": 94.63,
      "left_hip_angle": 83.05
    },
    {
      "frame_idx": 464,
      "timestamp": 7.7375,
      "right_knee_angle": 116.25,
      "left_knee_angle": null,
      "right_hip_angle": 103.31,
      "left_hip_angle": 90.13
    },
    {
      "frame_idx": 465,
      "timestamp": 7.7542,
      "right_knee_angle": 95.64,
      "left_knee_angle": 150.01,
      "right_hip_angle": 111.9,
      "left_hip_angle": 148.82
    },
    {
      "frame_idx": 466,
      "timestamp": 7.7709,
      "right_knee_angle": 179.04,
      "left_knee_angle": 171.01,
      "right_hip_angle": 172.95,
      "left_hip_angle": 166.25
    },
    {
      "frame_idx": 467,
      "timestamp": 7.7875,
      "right_knee_angle": 118.37,
      "left_knee_angle": null,
      "right_hip_angle": 105.54,
      "left_hip_angle": 101.48
    },
    {
      "frame_idx": 468,
      "timestamp": 7.8042,
      "right_knee_angle": null,
      "left_knee_angle": null,
      "right_hip_angle": 83.78,
      "left_hip_angle": null
    },
    {
      "frame_idx": 469,
      "timestamp": 7.8209,
      "right_knee_angle": 163.03,
      "left_knee_angle": 179.4,
      "right_hip_angle": 171.74,
      "left_hip_angle": 178.32
    },
    {
      "frame_idx": 470,
      "timestamp": 7.8376,
      "right_knee_angle": 111.78,
      "left_knee_angle": null,
      "right_hip_angle": 108.01,
      "left_hip_angle": null
    },
    {
      "frame_idx": 471,
      "timestamp": 7.8542,
      "right_knee_angle": 114.85,
      "left_knee_angle": 103.2,
      "right_hip_angle": 98.91,
      "left_hip_angle": 93.16
    },
    {
      "frame_idx": 472,
      "timestamp": 7.8709,
      "right_knee_angle": null,
      "left_knee_angle": null,
      "right_hip_angle": null,
      "left_hip_angle": null
    },
    {
      "frame_idx": 473,
      "timestamp": 7.8876,
      "right_knee_angle": 115.16,
      "left_knee_angle": null,
      "right_hip_angle": 94.3,
      "left_hip_angle": 93.81
    },
    {
      "frame_idx": 474,
      "timestamp": 7.9043,
      "right_knee_angle": 109.97,
      "left_knee_angle": 103.52,
      "right_hip_angle": 102.73,
      "left_hip_angle": 101.26
    },
    {
      "frame_idx": 475,
      "timestamp": 7.9209,
      "right_knee_angle": 118.32,
      "left_knee_angle": 116.14,
      "right_hip_angle": 107.21,
      "left_hip_angle": 109.68
    },
    {
      "frame_idx": 476,
      "timestamp": 7.9376,
      "right_knee_angle": 115.31,
      "left_knee_angle": 119.66,
      "right_hip_angle": 101.92,
      "left_hip_angle": 112.91
    },
    {
      "frame_idx": 477,
      "timestamp": 7.9543,
      "right_knee_angle": 110.22,
      "left_knee_angle": null,
      "right_hip_angle": 95.66,
      "left_hip_angle": 87.86
    },
    {
      "frame_idx": 478,
      "timestamp": 7.971,
      "right_knee_angle": 108.0,
      "left_knee_angle": 118.89,
      "right_hip_angle": 100.2,
      "left_hip_angle": 94.66
    },
    {
      "frame_idx": 479,
      "timestamp": 7.9877,
      "right_knee_angle": 111.92,
      "left_knee_angle": 107.65,
      "right_hip_angle": 101.34,
      "left_hip_angle": 97.33
    },
    {
      "frame_idx": 480,
      "timestamp": 8.0043,
      "right_knee_angle": 111.42,
      "left_knee_angle": null,
      "right_hip_angle": 101.57,
      "left_hip_angle": null
    },
    {
      "frame_idx": 481,
      "timestamp": 8.021,
      "right_knee_angle": 122.97,
      "left_knee_angle": null,
      "right_hip_angle": 109.31,
      "left_hip_angle": 126.27
    },
    {
      "frame_idx": 482,
      "timestamp": 8.0377,
      "right_knee_angle": 138.62,
      "left_knee_angle": 151.92,
      "right_hip_angle": 130.41,
      "left_hip_angle": 144.24
    },
    {
      "frame_idx": 483,
      "timestamp": 8.0544,
      "right_knee_angle": null,
      "left_knee_angle": null,
      "right_hip_angle": null,
      "left_hip_angle": null
    },
    {
      "frame_idx": 484,
      "timestamp": 8.071,
      "right_knee_angle": null,
      "left_knee_angle": null,
      "right_hip_angle": null,
      "left_hip_angle": null
    },
    {
      "frame_idx": 485,
      "timestamp": 8.0877,
      "right_knee_angle": 165.04,
      "left_knee_angle": 152.35,
      "right_hip_angle": 176.8,
      "left_hip_angle": 179.61
    },
    {
      "frame_idx": 486,
      "timestamp": 8.1044,
      "right_knee_angle": 174.7,
      "left_knee_angle": null,
      "right_hip_angle": 172.02,
      "left_hip_angle": null
    },
    {
      "frame_idx": 487,
      "timestamp": 8.1211,
      "right_knee_angle": 173.37,
      "left_knee_angle": null,
      "right_hip_angle": 177.68,
      "left_hip_angle": null
    },
    {
      "frame_idx": 488,
      "timestamp": 8.1377,
      "right_knee_angle": null,
      "left_knee_angle": null,
      "right_hip_angle": 135.15,
      "left_hip_angle": null
    },
    {
      "frame_idx": 489,
      "timestamp": 8.1544,
      "right_knee_angle": 119.28,
      "left_knee_angle": null,
      "right_hip_angle": 132.78,
      "left_hip_angle": 112.63
    },
    {
      "frame_idx": 490,
      "timestamp": 8.1711,
      "right_knee_angle": null,
      "left_knee_angle": null,
      "right_hip_angle": 125.33,
      "left_hip_angle": null
    },
    {
      "frame_idx": 491,
      "timestamp": 8.1878,
      "right_knee_angle": 155.23,
      "left_knee_angle": 79.62,
      "right_hip_angle": 153.5,
      "left_hip_angle": 105.68
    },
    {
      "frame_idx": 492,
      "timestamp": 8.2044,
      "right_knee_angle": 88.09,
      "left_knee_angle": null,
      "right_hip_angle": 88.88,
      "left_hip_angle": null
    },
    {
      "frame_idx": 499,
      "timestamp": 8.3212,
      "right_knee_angle": 133.01,
      "left_knee_angle": 115.83,
      "right_hip_angle": 120.23,
      "left_hip_angle": 108.51
    },
    {
      "frame_idx": 500,
      "timestamp": 8.3378,
      "right_knee_angle": 133.79,
      "left_knee_angle": 145.63,
      "right_hip_angle": 121.83,
      "left_hip_angle": 132.27
    },
    {
      "frame_idx": 501,
      "timestamp": 8.3545,
      "right_knee_angle": 131.1,
      "left_knee_angle": null,
      "right_hip_angle": 121.51,
      "left_hip_angle": null
    },
    {
      "frame_idx": 502,
      "timestamp": 8.3712,
      "right_knee_angle": 129.3,
      "left_knee_angle": 148.35,
      "right_hip_angle": 118.86,
      "left_hip_angle": 134.48
    },
    {
      "frame_idx": 503,
      "timestamp": 8.3879,
      "right_knee_angle": 113.23,
      "left_knee_angle": 130.95,
      "right_hip_angle": 108.28,
      "left_hip_angle": 114.1
    },
    {
      "frame_idx": 504,
      "timestamp": 8.4045,
      "right_knee_angle": 118.86,
      "left_knee_angle": 122.15,
      "right_hip_angle": 112.13,
      "left_hip_angle": 114.67
    },
    {
      "frame_idx": 505,
      "timestamp": 8.4212,
      "right_knee_angle": 104.93,
      "left_knee_angle": 127.23,
      "right_hip_angle": 113.25,
      "left_hip_angle": 116.58
    },
    {
      "frame_idx": 506,
      "timestamp": 8.4379,
      "right_knee_angle": 93.89,
      "left_knee_angle": 116.26,
      "right_hip_angle": 96.59,
      "left_hip_angle": 103.9
    },
    {
      "frame_idx": 507,
      "timestamp": 8.4546,
      "right_knee_angle": 107.39,
      "left_knee_angle": 119.61,
      "right_hip_angle": 105.65,
      "left_hip_angle": 105.75
    },
    {
      "frame_idx": 508,
      "timestamp": 8.4712,
      "right_knee_angle": 102.71,
      "left_knee_angle": 124.82,
      "right_hip_angle": 102.14,
      "left_hip_angle": 103.08
    },
    {
      "frame_idx": 509,
      "timestamp": 8.4879,
      "right_knee_angle": 91.81,
      "left_knee_angle": 117.5,
      "right_hip_angle": 98.42,
      "left_hip_angle": 99.17
    },
    {
      "frame_idx": 510,
      "timestamp": 8.5046,
      "right_knee_angle": 89.91,
      "left_knee_angle": 118.96,
      "right_hip_angle": 98.9,
      "left_hip_angle": 104.42
    },
    {
      "frame_idx": 511,
      "timestamp": 8.5213,
      "right_knee_angle": 93.87,
      "left_knee_angle": 122.33,
      "right_hip_angle": 100.85,
      "left_hip_angle": 103.14
    },
    {
      "frame_idx": 512,
      "timestamp": 8.5379,
      "right_knee_angle": 108.15,
      "left_knee_angle": 90.54,
      "right_hip_angle": 88.65,
      "left_hip_angle": 98.21
    },
    {
      "frame_idx": 513,
      "timestamp": 8.5546,
      "right_knee_angle": 114.17,
      "left_knee_angle": null,
      "right_hip_angle": 95.26,
      "left_hip_angle": 95.53
    },
    {
      "frame_idx": 514,
      "timestamp": 8.5713,
      "right_knee_angle": 109.53,
      "left_knee_angle": null,
      "right_hip_angle": 88.15,
      "left_hip_angle": 91.73
    },
    {
      "frame_idx": 515,
      "timestamp": 8.588,
      "right_knee_angle": 112.78,
      "left_knee_angle": null,
      "right_hip_angle": 102.03,
      "left_hip_angle": null
    },
    {
      "frame_idx": 516,
      "timestamp": 8.6047,
      "right_knee_angle": 143.23,
      "left_knee_angle": 152.66,
      "right_hip_angle": 121.95,
      "left_hip_angle": 142.65
    },
    {
      "frame_idx": 517,
      "timestamp": 8.6213,
      "right_knee_angle": 127.54,
      "left_knee_angle": null,
      "right_hip_angle": 111.9,
      "left_hip_angle": null
    },
    {
      "frame_idx": 518,
      "timestamp": 8.638,
      "right_knee_angle": 117.71,
      "left_knee_angle": null,
      "right_hip_angle": 106.62,
      "left_hip_angle": null
    },
    {
      "frame_idx": 519,
      "timestamp": 8.6547,
      "right_knee_angle": 109.6,
      "left_knee_angle": null,
      "right_hip_angle": 86.51,
      "left_hip_angle": null
    },
    {
      "frame_idx": 520,
      "timestamp": 8.6714,
      "right_knee_angle": 103.69,
      "left_knee_angle": 105.6,
      "right_hip_angle": 82.48,
      "left_hip_angle": 88.23
    },
    {
      "frame_idx": 521,
      "timestamp": 8.688,
      "right_knee_angle": 105.2,
      "left_knee_angle": null,
      "right_hip_angle": 82.26,
      "left_hip_angle": 90.04
    },
    {
      "frame_idx": 522,
      "timestamp": 8.7047,
      "right_knee_angle": 102.85,
      "left_knee_angle": null,
      "right_hip_angle": 87.04,
      "left_hip_angle": 83.16
    },
    {
      "frame_idx": 523,
      "timestamp": 8.7214,
      "right_knee_angle": 100.08,
      "left_knee_angle": 144.5,
      "right_hip_angle": 86.45,
      "left_hip_angle": 83.37
    },
    {
      "frame_idx": 524,
      "timestamp": 8.7381,
      "right_knee_angle": 107.38,
      "left_knee_angle": 116.07,
      "right_hip_angle": 88.34,
      "left_hip_angle": 91.88
    },
    {
      "frame_idx": 525,
      "timestamp": 8.7547,
      "right_knee_angle": null,
      "left_knee_angle": null,
      "right_hip_angle": null,
      "left_hip_angle": null
    },
    {
      "frame_idx": 526,
      "timestamp": 8.7714,
      "right_knee_angle": 79.35,
      "left_knee_angle": null,
      "right_hip_angle": 99.37,
      "left_hip_angle": 82.37
    },
    {
      "frame_idx": 527,
      "timestamp": 8.7881,
      "right_knee_angle": 103.94,
      "left_knee_angle": null,
      "right_hip_angle": 90.09,
      "left_hip_angle": null
    },
    {
      "frame_idx": 528,
      "timestamp": 8.8048,
      "right_knee_angle": 118.28,
      "left_knee_angle": null,
      "right_hip_angle": 106.56,
      "left_hip_angle": 99.54
    },
    {
      "frame_idx": 529,
      "timestamp": 8.8214,
      "right_knee_angle": null,
      "left_knee_angle": null,
      "right_hip_angle": null,
      "left_hip_angle": null
    },
    {
      "frame_idx": 530,
      "timestamp": 8.8381,
      "right_knee_angle": 128.05,
      "left_knee_angle": null,
      "right_hip_angle": 111.98,
      "left_hip_angle": 101.59
    },
    {
      "frame_idx": 531,
      "timestamp": 8.8548,
      "right_knee_angle": 135.34,
      "left_knee_angle": null,
      "right_hip_angle": 109.19,
      "left_hip_angle": 101.15
    },
    {
      "frame_idx": 532,
      "timestamp": 8.8715,
      "right_knee_angle": 136.81,
      "left_knee_angle": null,
      "right_hip_angle": 115.35,
      "left_hip_angle": null
    },
    {
      "frame_idx": 533,
      "timestamp": 8.8881,
      "right_knee_angle": 136.45,
      "left_knee_angle": null,
      "right_hip_angle": 115.51,
      "left_hip_angle": null
    },
    {
      "frame_idx": 534,
      "timestamp": 8.9048,
      "right_knee_angle": null,
      "left_knee_angle": null,
      "right_hip_angle": null,
      "left_hip_angle": null
    },
    {
      "frame_idx": 535,
      "timestamp": 8.9215,
      "right_knee_angle": 138.6,
      "left_knee_angle": null,
      "right_hip_angle": 111.31,
      "left_hip_angle": 123.9
    },
    {
      "frame_idx": 536,
      "timestamp": 8.9382,
      "right_knee_angle": null,
      "left_knee_angle": null,
      "right_hip_angle": null,
      "left_hip_angle": null
    },
    {
      "frame_idx": 537,
      "timestamp": 8.9548,
      "right_knee_angle": 141.71,
      "left_knee_angle": null,
      "right_hip_angle": 127.08,
      "left_hip_angle": null
    },
    {
      "frame_idx": 538,
      "timestamp": 8.9715,
      "right_knee_angle": 142.41,
      "left_knee_angle": null,
      "right_hip_angle": 129.89,
      "left_hip_angle": null
    },
    {
      "frame_idx": 539,
      "timestamp": 8.9882,
      "right_knee_angle": 46.68,
      "left_knee_angle": 82.69,
      "right_hip_angle": 82.92,
      "left_hip_angle": 101.09
    },
    {
      "frame_idx": 540,
      "timestamp": 9.0049,
      "right_knee_angle": 145.03,
      "left_knee_angle": null,
      "right_hip_angle": 120.28,
      "left_hip_angle": 82.3
    },
    {
      "frame_idx": 541,
      "timestamp": 9.0215,
      "right_knee_angle": 138.69,
      "left_knee_angle": 68.86,
      "right_hip_angle": 130.27,
      "left_hip_angle": 89.1
    },
    {
      "frame_idx": 542,
      "timestamp": 9.0382,
      "right_knee_angle": 125.01,
      "left_knee_angle": 81.65,
      "right_hip_angle": 119.02,
      "left_hip_angle": 82.87
    },
    {
      "frame_idx": 543,
      "timestamp": 9.0549,
      "right_knee_angle": null,
      "left_knee_angle": null,
      "right_hip_angle": null,
      "left_hip_angle": null
    },
    {
      "frame_idx": 544,
      "timestamp": 9.0716,
      "right_knee_angle": 118.4,
      "left_knee_angle": 133.58,
      "right_hip_angle": 128.99,
      "left_hip_angle": 146.88
    },
    {
      "frame_idx": 545,
      "timestamp": 9.0882,
      "right_knee_angle": 115.6,
      "left_knee_angle": null,
      "right_hip_angle": 113.48,
      "left_hip_angle": 89.73
    },
    {
      "frame_idx": 546,
      "timestamp": 9.1049,
      "right_knee_angle": 123.34,
      "left_knee_angle": null,
      "right_hip_angle": 114.56,
      "left_hip_angle": 103.07
    },
    {
      "frame_idx": 547,
      "timestamp": 9.1216,
      "right_knee_angle": 103.53,
      "left_knee_angle": 111.02,
      "right_hip_angle": 108.65,
      "left_hip_angle": 105.28
    },
    {
      "frame_idx": 548,
      "timestamp": 9.1383,
      "right_knee_angle": 107.12,
      "left_knee_angle": 122.14,
      "right_hip_angle": 107.33,
      "left_hip_angle": 111.97
    },
    {
      "frame_idx": 549,
      "timestamp": 9.1549,
      "right_knee_angle": 106.18,
      "left_knee_angle": 127.66,
      "right_hip_angle": 111.79,
      "left_hip_angle": 115.27
    },
    {
      "frame_idx": 550,
      "timestamp": 9.1716,
      "right_knee_angle": 113.01,
      "left_knee_angle": 109.1,
      "right_hip_angle": 104.42,
      "left_hip_angle": 100.53
    },
    {
      "frame_idx": 551,
      "timestamp": 9.1883,
      "right_knee_angle": 107.49,
      "left_knee_angle": 107.5,
      "right_hip_angle": 96.76,
      "left_hip_angle": 98.7
    },
    {
      "frame_idx": 552,
      "timestamp": 9.205,
      "right_knee_angle": 110.18,
      "left_knee_angle": 110.0,
      "right_hip_angle": 100.78,
      "left_hip_angle": 95.56
    },
    {
      "frame_idx": 553,
      "timestamp": 9.2217,
      "right_knee_angle": 113.26,
      "left_knee_angle": null,
      "right_hip_angle": 98.16,
      "left_hip_angle": 94.73
    },
    {
      "frame_idx": 554,
      "timestamp": 9.2383,
      "right_knee_angle": 104.76,
      "left_knee_angle": 150.74,
      "right_hip_angle": 96.04,
      "left_hip_angle": 128.05
    },
    {
      "frame_idx": 555,
      "timestamp": 9.255,
      "right_knee_angle": 107.45,
      "left_knee_angle": null,
      "right_hip_angle": 95.52,
      "left_hip_angle": 101.44
    },
    {
      "frame_idx": 556,
      "timestamp": 9.2717,
      "right_knee_angle": 99.66,
      "left_knee_angle": 143.11,
      "right_hip_angle": 85.76,
      "left_hip_angle": 124.39
    },
    {
      "frame_idx": 557,
      "timestamp": 9.2884,
      "right_knee_angle": 96.92,
      "left_knee_angle": 141.95,
      "right_hip_angle": 91.67,
      "left_hip_angle": 127.03
    },
    {
      "frame_idx": 558,
      "timestamp": 9.305,
      "right_knee_angle": 94.99,
      "left_knee_angle": null,
      "right_hip_angle": 78.95,
      "left_hip_angle": null
    },
    {
      "frame_idx": 559,
      "timestamp": 9.3217,
      "right_knee_angle": 93.01,
      "left_knee_angle": 139.38,
      "right_hip_angle": 80.71,
      "left_hip_angle": 112.7
    },
    {
      "frame_idx": 560,
      "timestamp": 9.3384,
      "right_knee_angle": 96.46,
      "left_knee_angle": 134.71,
      "right_hip_angle": 78.51,
      "left_hip_angle": 112.43
    },
    {
      "frame_idx": 561,
      "timestamp": 9.3551,
      "right_knee_angle": 93.7,
      "left_knee_angle": 138.3,
      "right_hip_angle": 77.59,
      "left_hip_angle": 115.18
    },
    {
      "frame_idx": 562,
      "timestamp": 9.3717,
      "right_knee_angle": 87.37,
      "left_knee_angle": null,
      "right_hip_angle": 74.29,
      "left_hip_angle": 86.15
    },
    {
      "frame_idx": 563,
      "timestamp": 9.3884,
      "right_knee_angle": 89.65,
      "left_knee_angle": null,
      "right_hip_angle": 76.93,
      "left_hip_angle": null
    },
    {
      "frame_idx": 564,
      "timestamp": 9.4051,
      "right_knee_angle": null,
      "left_knee_angle": null,
      "right_hip_angle": 78.05,
      "left_hip_angle": null
    },
    {
      "frame_idx": 565,
      "timestamp": 9.4218,
      "right_knee_angle": null,
      "left_knee_angle": null,
      "right_hip_angle": 79.39,
      "left_hip_angle": 116.46
    },
    {
      "frame_idx": 566,
      "timestamp": 9.4384,
      "right_knee_angle": 132.4,
      "left_knee_angle": null,
      "right_hip_angle": 142.14,
      "left_hip_angle": 101.56
    },
    {
      "frame_idx": 567,
      "timestamp": 9.4551,
      "right_knee_angle": 89.1,
      "left_knee_angle": 108.99,
      "right_hip_angle": 89.55,
      "left_hip_angle": 101.97
    },
    {
      "frame_idx": 568,
      "timestamp": 9.4718,
      "right_knee_angle": null,
      "left_knee_angle": null,
      "right_hip_angle": 79.46,
      "left_hip_angle": null
    },
    {
      "frame_idx": 569,
      "timestamp": 9.4885,
      "right_knee_angle": 102.53,
      "left_knee_angle": 93.4,
      "right_hip_angle": 89.44,
      "left_hip_angle": 86.48
    },
    {
      "frame_idx": 570,
      "timestamp": 9.5051,
      "right_knee_angle": 114.5,
      "left_knee_angle": 87.49,
      "right_hip_angle": 102.44,
      "left_hip_angle": 91.91
    },
    {
      "frame_idx": 571,
      "timestamp": 9.5218,
      "right_knee_angle": null,
      "left_knee_angle": null,
      "right_hip_angle": null,
      "left_hip_angle": null
    },
    {
      "frame_idx": 572,
      "timestamp": 9.5385,
      "right_knee_angle": 113.59,
      "left_knee_angle": 86.71,
      "right_hip_angle": 98.36,
      "left_hip_angle": 99.16
    },
    {
      "frame_idx": 573,
      "timestamp": 9.5552,
      "right_knee_angle": 80.71,
      "left_knee_angle": null,
      "right_hip_angle": 90.42,
      "left_hip_angle": 73.44
    },
    {
      "frame_idx": 574,
      "timestamp": 9.5718,
      "right_knee_angle": 119.22,
      "left_knee_angle": 89.51,
      "right_hip_angle": 103.8,
      "left_hip_angle": 116.35
    },
    {
      "frame_idx": 575,
      "timestamp": 9.5885,
      "right_knee_angle": 88.71,
      "left_knee_angle": 87.47,
      "right_hip_angle": 94.64,
      "left_hip_angle": 95.21
    },
    {
      "frame_idx": 576,
      "timestamp": 9.6052,
      "right_knee_angle": 122.92,
      "left_knee_angle": 92.09,
      "right_hip_angle": 102.67,
      "left_hip_angle": 117.73
    },
    {
      "frame_idx": 577,
      "timestamp": 9.6219,
      "right_knee_angle": 126.47,
      "left_knee_angle": 96.73,
      "right_hip_angle": 107.33,
      "left_hip_angle": 118.1
    },
    {
      "frame_idx": 578,
      "timestamp": 9.6385,
      "right_knee_angle": 123.63,
      "left_knee_angle": 90.77,
      "right_hip_angle": 98.95,
      "left_hip_angle": 101.12
    },
    {
      "frame_idx": 579,
      "timestamp": 9.6552,
      "right_knee_angle": 129.52,
      "left_knee_angle": null,
      "right_hip_angle": 102.75,
      "left_hip_angle": null
    },
    {
      "frame_idx": 580,
      "timestamp": 9.6719,
      "right_knee_angle": 132.62,
      "left_knee_angle": 110.98,
      "right_hip_angle": 109.27,
      "left_hip_angle": 136.82
    },
    {
      "frame_idx": 581,
      "timestamp": 9.6886,
      "right_knee_angle": 131.91,
      "left_knee_angle": null,
      "right_hip_angle": 110.1,
      "left_hip_angle": null
    },
    {
      "frame_idx": 582,
      "timestamp": 9.7052,
      "right_knee_angle": null,
      "left_knee_angle": null,
      "right_hip_angle": 113.99,
      "left_hip_angle": null
    },
    {
      "frame_idx": 583,
      "timestamp": 9.7219,
      "right_knee_angle": 137.55,
      "left_knee_angle": null,
      "right_hip_angle": 108.86,
      "left_hip_angle": null
    },
    {
      "frame_idx": 584,
      "timestamp": 9.7386,
      "right_knee_angle": 130.96,
      "left_knee_angle": null,
      "right_hip_angle": 102.93,
      "left_hip_angle": 94.32
    },
    {
      "frame_idx": 585,
      "timestamp": 9.7553,
      "right_knee_angle": 113.96,
      "left_knee_angle": null,
      "right_hip_angle": 102.61,
      "left_hip_angle": 97.53
    },
    {
      "frame_idx": 586,
      "timestamp": 9.772,
      "right_knee_angle": 131.83,
      "left_knee_angle": 108.81,
      "right_hip_angle": 108.48,
      "left_hip_angle": 115.5
    },
    {
      "frame_idx": 587,
      "timestamp": 9.7886,
      "right_knee_angle": 114.28,
      "left_knee_angle": null,
      "right_hip_angle": 118.45,
      "left_hip_angle": null
    },
    {
      "frame_idx": 588,
      "timestamp": 9.8053,
      "right_knee_angle": 127.36,
      "left_knee_angle": null,
      "right_hip_angle": 113.05,
      "left_hip_angle": 92.53
    },
    {
      "frame_idx": 589,
      "timestamp": 9.822,
      "right_knee_angle": null,
      "left_knee_angle": null,
      "right_hip_angle": 104.18,
      "left_hip_angle": 91.78
    },
    {
      "frame_idx": 590,
      "timestamp": 9.8387,
      "right_knee_angle": 121.16,
      "left_knee_angle": 106.83,
      "right_hip_angle": 117.58,
      "left_hip_angle": 96.51
    },
    {
      "frame_idx": 591,
      "timestamp": 9.8553,
      "right_knee_angle": 122.87,
      "left_knee_angle": null,
      "right_hip_angle": null,
      "left_hip_angle": null
    },
    {
      "frame_idx": 592,
      "timestamp": 9.872,
      "right_knee_angle": 121.34,
      "left_knee_angle": 113.52,
      "right_hip_angle": 104.91,
      "left_hip_angle": 105.08
    },
    {
      "frame_idx": 593,
      "timestamp": 9.8887,
      "right_knee_angle": 112.68,
      "left_knee_angle": 126.06,
      "right_hip_angle": 97.84,
      "left_hip_angle": 102.26
    },
    {
      "frame_idx": 594,
      "timestamp": 9.9054,
      "right_knee_angle": 108.98,
      "left_knee_angle": 83.25,
      "right_hip_angle": 100.71,
      "left_hip_angle": 94.01
    },
    {
      "frame_idx": 595,
      "timestamp": 9.922,
      "right_knee_angle": 104.09,
      "left_knee_angle": null,
      "right_hip_angle": 95.76,
      "left_hip_angle": null
    },
    {
      "frame_idx": 596,
      "timestamp": 9.9387,
      "right_knee_angle": 102.63,
      "left_knee_angle": null,
      "right_hip_angle": 89.02,
      "left_hip_angle": 123.54
    },
    {
      "frame_idx": 597,
      "timestamp": 9.9554,
      "right_knee_angle": 111.0,
      "left_knee_angle": null,
      "right_hip_angle": 92.65,
      "left_hip_angle": 104.61
    },
    {
      "frame_idx": 598,
      "timestamp": 9.9721,
      "right_knee_angle": 104.79,
      "left_knee_angle": null,
      "right_hip_angle": 98.07,
      "left_hip_angle": 107.12
    },
    {
      "frame_idx": 599,
      "timestamp": 9.9887,
      "right_knee_angle": 97.22,
      "left_knee_angle": null,
      "right_hip_angle": 87.4,
      "left_hip_angle": 96.76
    },
    {
      "frame_idx": 600,
      "timestamp": 10.0054,
      "right_knee_angle": null,
      "left_knee_angle": null,
      "right_hip_angle": null,
      "left_hip_angle": null
    },
    {
      "frame_idx": 601,
      "timestamp": 10.0221,
      "right_knee_angle": null,
      "left_knee_angle": null,
      "right_hip_angle": null,
      "left_hip_angle": null
    },
    {
      "frame_idx": 602,
      "timestamp": 10.0388,
      "right_knee_angle": null,
      "left_knee_angle": null,
      "right_hip_angle": null,
      "left_hip_angle": null
    },
    {
      "frame_idx": 603,
      "timestamp": 10.0554,
      "right_knee_angle": 81.37,
      "left_knee_angle": null,
      "right_hip_angle": 73.09,
      "left_hip_angle": null
    },
    {
      "frame_idx": 604,
      "timestamp": 10.0721,
      "right_knee_angle": 78.95,
      "left_knee_angle": 144.88,
      "right_hip_angle": 69.59,
      "left_hip_angle": 127.89
    },
    {
      "frame_idx": 605,
      "timestamp": 10.0888,
      "right_knee_angle": 85.35,
      "left_knee_angle": null,
      "right_hip_angle": 78.75,
      "left_hip_angle": null
    },
    {
      "frame_idx": 606,
      "timestamp": 10.1055,
      "right_knee_angle": 78.98,
      "left_knee_angle": null,
      "right_hip_angle": 72.1,
      "left_hip_angle": 69.07
    },
    {
      "frame_idx": 607,
      "timestamp": 10.1221,
      "right_knee_angle": null,
      "left_knee_angle": null,
      "right_hip_angle": null,
      "left_hip_angle": null
    },
    {
      "frame_idx": 608,
      "timestamp": 10.1388,
      "right_knee_angle": null,
      "left_knee_angle": null,
      "right_hip_angle": null,
      "left_hip_angle": null
    },
    {
      "frame_idx": 609,
      "timestamp": 10.1555,
      "right_knee_angle": null,
      "left_knee_angle": null,
      "right_hip_angle": null,
      "left_hip_angle": null
    },
    {
      "frame_idx": 610,
      "timestamp": 10.1722,
      "right_knee_angle": 88.45,
      "left_knee_angle": null,
      "right_hip_angle": 78.37,
      "left_hip_angle": null
    },
    {
      "frame_idx": 611,
      "timestamp": 10.1888,
      "right_knee_angle": null,
      "left_knee_angle": null,
      "right_hip_angle": null,
      "left_hip_angle": null
    },
    {
      "frame_idx": 612,
      "timestamp": 10.2055,
      "right_knee_angle": null,
      "left_knee_angle": null,
      "right_hip_angle": null,
      "left_hip_angle": null
    },
    {
      "frame_idx": 613,
      "timestamp": 10.2222,
      "right_knee_angle": null,
      "left_knee_angle": null,
      "right_hip_angle": 75.8,
      "left_hip_angle": null
    },
    {
      "frame_idx": 614,
      "timestamp": 10.2389,
      "right_knee_angle": null,
      "left_knee_angle": null,
      "right_hip_angle": null,
      "left_hip_angle": null
    },
    {
      "frame_idx": 615,
      "timestamp": 10.2555,
      "right_knee_angle": null,
      "left_knee_angle": null,
      "right_hip_angle": null,
      "left_hip_angle": null
    },
    {
      "frame_idx": 616,
      "timestamp": 10.2722,
      "right_knee_angle": 116.86,
      "left_knee_angle": 98.2,
      "right_hip_angle": 121.28,
      "left_hip_angle": 108.94
    },
    {
      "frame_idx": 617,
      "timestamp": 10.2889,
      "right_knee_angle": 115.94,
      "left_knee_angle": null,
      "right_hip_angle": 136.07,
      "left_hip_angle": null
    },
    {
      "frame_idx": 618,
      "timestamp": 10.3056,
      "right_knee_angle": null,
      "left_knee_angle": null,
      "right_hip_angle": null,
      "left_hip_angle": null
    },
    {
      "frame_idx": 619,
      "timestamp": 10.3222,
      "right_knee_angle": 112.17,
      "left_knee_angle": 128.4,
      "right_hip_angle": 91.27,
      "left_hip_angle": 128.08
    },
    {
      "frame_idx": 620,
      "timestamp": 10.3389,
      "right_knee_angle": 97.47,
      "left_knee_angle": null,
      "right_hip_angle": 107.22,
      "left_hip_angle": 101.51
    },
    {
      "frame_idx": 621,
      "timestamp": 10.3556,
      "right_knee_angle": 113.96,
      "left_knee_angle": 115.36,
      "right_hip_angle": 102.9,
      "left_hip_angle": 125.74
    },
    {
      "frame_idx": 622,
      "timestamp": 10.3723,
      "right_knee_angle": 78.18,
      "left_knee_angle": null,
      "right_hip_angle": 104.15,
      "left_hip_angle": null
    },
    {
      "frame_idx": 623,
      "timestamp": 10.389,
      "right_knee_angle": 100.71,
      "left_knee_angle": 94.05,
      "right_hip_angle": 117.85,
      "left_hip_angle": null
    },
    {
      "frame_idx": 624,
      "timestamp": 10.4056,
      "right_knee_angle": 75.31,
      "left_knee_angle": 85.53,
      "right_hip_angle": 91.43,
      "left_hip_angle": 101.34
    },
    {
      "frame_idx": 625,
      "timestamp": 10.4223,
      "right_knee_angle": 121.78,
      "left_knee_angle": 83.01,
      "right_hip_angle": 113.29,
      "left_hip_angle": 120.98
    },
    {
      "frame_idx": 626,
      "timestamp": 10.439,
      "right_knee_angle": 117.2,
      "left_knee_angle": null,
      "right_hip_angle": 131.37,
      "left_hip_angle": null
    },
    {
      "frame_idx": 627,
      "timestamp": 10.4557,
      "right_knee_angle": 96.04,
      "left_knee_angle": 111.04,
      "right_hip_angle": 120.55,
      "left_hip_angle": 136.46
    },
    {
      "frame_idx": 628,
      "timestamp": 10.4723,
      "right_knee_angle": null,
      "left_knee_angle": null,
      "right_hip_angle": null,
      "left_hip_angle": null
    },
    {
      "frame_idx": 629,
      "timestamp": 10.489,
      "right_knee_angle": 155.71,
      "left_knee_angle": 174.01,
      "right_hip_angle": null,
      "left_hip_angle": 174.32
    },
    {
      "frame_idx": 630,
      "timestamp": 10.5057,
      "right_knee_angle": 145.78,
      "left_knee_angle": 136.35,
      "right_hip_angle": 94.05,
      "left_hip_angle": 103.72
    },
    {
      "frame_idx": 631,
      "timestamp": 10.5224,
      "right_knee_angle": null,
      "left_knee_angle": null,
      "right_hip_angle": null,
      "left_hip_angle": null
    },
    {
      "frame_idx": 632,
      "timestamp": 10.539,
      "right_knee_angle": 132.84,
      "left_knee_angle": null,
      "right_hip_angle": 111.11,
      "left_hip_angle": null
    },
    {
      "frame_idx": 633,
      "timestamp": 10.5557,
      "right_knee_angle": null,
      "left_knee_angle": null,
      "right_hip_angle": null,
      "left_hip_angle": null
    },
    {
      "frame_idx": 634,
      "timestamp": 10.5724,
      "right_knee_angle": null,
      "left_knee_angle": null,
      "right_hip_angle": null,
      "left_hip_angle": null
    },
    {
      "frame_idx": 635,
      "timestamp": 10.5891,
      "right_knee_angle": 175.44,
      "left_knee_angle": null,
      "right_hip_angle": null,
      "left_hip_angle": null
    },
    {
      "frame_idx": 636,
      "timestamp": 10.6057,
      "right_knee_angle": 127.81,
      "left_knee_angle": 156.56,
      "right_hip_angle": 114.68,
      "left_hip_angle": 143.0
    },
    {
      "frame_idx": 1178,
      "timestamp": 19.644,
      "right_knee_angle": null,
      "left_knee_angle": 129.59,
      "right_hip_angle": 111.8,
      "left_hip_angle": 121.97
    },
    {
      "frame_idx": 1179,
      "timestamp": 19.6606,
      "right_knee_angle": null,
      "left_knee_angle": 134.7,
      "right_hip_angle": 110.87,
      "left_hip_angle": 122.21
    },
    {
      "frame_idx": 1180,
      "timestamp": 19.6773,
      "right_knee_angle": 88.62,
      "left_knee_angle": 135.0,
      "right_hip_angle": 104.54,
      "left_hip_angle": 122.28
    },
    {
      "frame_idx": 1181,
      "timestamp": 19.694,
      "right_knee_angle": 86.6,
      "left_knee_angle": 135.38,
      "right_hip_angle": 107.92,
      "left_hip_angle": 120.18
    },
    {
      "frame_idx": 1182,
      "timestamp": 19.7107,
      "right_knee_angle": 81.51,
      "left_knee_angle": 135.07,
      "right_hip_angle": 96.1,
      "left_hip_angle": 123.02
    },
    {
      "frame_idx": 1183,
      "timestamp": 19.7273,
      "right_knee_angle": 86.82,
      "left_knee_angle": 141.85,
      "right_hip_angle": 94.94,
      "left_hip_angle": 124.93
    },
    {
      "frame_idx": 1184,
      "timestamp": 19.744,
      "right_knee_angle": 88.3,
      "left_knee_angle": 143.05,
      "right_hip_angle": 94.47,
      "left_hip_angle": 127.92
    },
    {
      "frame_idx": 1185,
      "timestamp": 19.7607,
      "right_knee_angle": 99.18,
      "left_knee_angle": 141.49,
      "right_hip_angle": 97.22,
      "left_hip_angle": 127.25
    },
    {
      "frame_idx": 1186,
      "timestamp": 19.7774,
      "right_knee_angle": 83.39,
      "left_knee_angle": 138.78,
      "right_hip_angle": 89.51,
      "left_hip_angle": 124.61
    },
    {
      "frame_idx": 1187,
      "timestamp": 19.794,
      "right_knee_angle": 81.39,
      "left_knee_angle": 138.85,
      "right_hip_angle": 86.95,
      "left_hip_angle": 125.4
    },
    {
      "frame_idx": 1188,
      "timestamp": 19.8107,
      "right_knee_angle": 80.93,
      "left_knee_angle": 136.66,
      "right_hip_angle": 80.4,
      "left_hip_angle": 125.49
    },
    {
      "frame_idx": 1189,
      "timestamp": 19.8274,
      "right_knee_angle": 86.79,
      "left_knee_angle": 130.43,
      "right_hip_angle": 83.24,
      "left_hip_angle": 123.52
    },
    {
      "frame_idx": 1190,
      "timestamp": 19.8441,
      "right_knee_angle": 92.17,
      "left_knee_angle": 127.79,
      "right_hip_angle": 85.77,
      "left_hip_angle": 122.01
    },
    {
      "frame_idx": 1191,
      "timestamp": 19.8607,
      "right_knee_angle": 93.59,
      "left_knee_angle": 123.99,
      "right_hip_angle": 86.07,
      "left_hip_angle": 119.39
    },
    {
      "frame_idx": 1192,
      "timestamp": 19.8774,
      "right_knee_angle": 94.92,
      "left_knee_angle": 118.02,
      "right_hip_angle": 86.34,
      "left_hip_angle": 118.03
    },
    {
      "frame_idx": 1193,
      "timestamp": 19.8941,
      "right_knee_angle": 102.37,
      "left_knee_angle": 117.53,
      "right_hip_angle": 90.71,
      "left_hip_angle": 118.3
    },
    {
      "frame_idx": 1194,
      "timestamp": 19.9108,
      "right_knee_angle": 108.17,
      "left_knee_angle": 109.71,
      "right_hip_angle": 97.0,
      "left_hip_angle": 113.8
    },
    {
      "frame_idx": 1195,
      "timestamp": 19.9274,
      "right_knee_angle": 111.46,
      "left_knee_angle": 106.11,
      "right_hip_angle": 101.27,
      "left_hip_angle": 114.14
    },
    {
      "frame_idx": 1196,
      "timestamp": 19.9441,
      "right_knee_angle": 115.94,
      "left_knee_angle": 101.68,
      "right_hip_angle": 103.44,
      "left_hip_angle": 110.19
    },
    {
      "frame_idx": 1197,
      "timestamp": 19.9608,
      "right_knee_angle": 114.83,
      "left_knee_angle": 98.24,
      "right_hip_angle": 107.46,
      "left_hip_angle": 110.79
    },
    {
      "frame_idx": 1198,
      "timestamp": 19.9775,
      "right_knee_angle": 118.97,
      "left_knee_angle": 94.02,
      "right_hip_angle": 108.16,
      "left_hip_angle": 108.52
    },
    {
      "frame_idx": 1199,
      "timestamp": 19.9941,
      "right_knee_angle": 116.06,
      "left_knee_angle": 90.24,
      "right_hip_angle": 108.33,
      "left_hip_angle": 105.45
    },
    {
      "frame_idx": 1200,
      "timestamp": 20.0108,
      "right_knee_angle": 125.46,
      "left_knee_angle": 89.55,
      "right_hip_angle": 114.25,
      "left_hip_angle": 105.67
    },
    {
      "frame_idx": 1201,
      "timestamp": 20.0275,
      "right_knee_angle": 125.3,
      "left_knee_angle": 82.99,
      "right_hip_angle": 111.02,
      "left_hip_angle": 102.54
    },
    {
      "frame_idx": 1202,
      "timestamp": 20.0442,
      "right_knee_angle": 127.39,
      "left_knee_angle": 84.52,
      "right_hip_angle": 110.78,
      "left_hip_angle": 100.69
    },
    {
      "frame_idx": 1203,
      "timestamp": 20.0608,
      "right_knee_angle": 132.63,
      "left_knee_angle": 82.31,
      "right_hip_angle": 114.73,
      "left_hip_angle": 97.25
    },
    {
      "frame_idx": 1204,
      "timestamp": 20.0775,
      "right_knee_angle": 140.55,
      "left_knee_angle": 79.55,
      "right_hip_angle": 122.42,
      "left_hip_angle": 95.13
    },
    {
      "frame_idx": 1205,
      "timestamp": 20.0942,
      "right_knee_angle": 144.13,
      "left_knee_angle": 75.28,
      "right_hip_angle": 125.09,
      "left_hip_angle": 91.85
    },
    {
      "frame_idx": 1206,
      "timestamp": 20.1109,
      "right_knee_angle": 145.58,
      "left_knee_angle": 72.75,
      "right_hip_angle": 130.09,
      "left_hip_angle": 87.22
    },
    {
      "frame_idx": 1207,
      "timestamp": 20.1275,
      "right_knee_angle": 143.52,
      "left_knee_angle": 73.03,
      "right_hip_angle": 131.77,
      "left_hip_angle": 85.59
    },
    {
      "frame_idx": 1208,
      "timestamp": 20.1442,
      "right_knee_angle": 150.53,
      "left_knee_angle": 72.95,
      "right_hip_angle": 131.84,
      "left_hip_angle": 83.44
    },
    {
      "frame_idx": 1209,
      "timestamp": 20.1609,
      "right_knee_angle": null,
      "left_knee_angle": 76.92,
      "right_hip_angle": 133.71,
      "left_hip_angle": 80.7
    },
    {
      "frame_idx": 1210,
      "timestamp": 20.1776,
      "right_knee_angle": 145.83,
      "left_knee_angle": 77.16,
      "right_hip_angle": 129.99,
      "left_hip_angle": 81.05
    },
    {
      "frame_idx": 1211,
      "timestamp": 20.1943,
      "right_knee_angle": 150.52,
      "left_knee_angle": 75.41,
      "right_hip_angle": 130.89,
      "left_hip_angle": 77.94
    },
    {
      "frame_idx": 1212,
      "timestamp": 20.2109,
      "right_knee_angle": 139.33,
      "left_knee_angle": 77.85,
      "right_hip_angle": 125.21,
      "left_hip_angle": 77.28
    },
    {
      "frame_idx": 1213,
      "timestamp": 20.2276,
      "right_knee_angle": 137.68,
      "left_knee_angle": 81.07,
      "right_hip_angle": 130.0,
      "left_hip_angle": 76.69
    },
    {
      "frame_idx": 1214,
      "timestamp": 20.2443,
      "right_knee_angle": 132.13,
      "left_knee_angle": 83.29,
      "right_hip_angle": 121.86,
      "left_hip_angle": 76.24
    },
    {
      "frame_idx": 1215,
      "timestamp": 20.261,
      "right_knee_angle": 132.8,
      "left_knee_angle": 83.96,
      "right_hip_angle": 129.62,
      "left_hip_angle": 77.81
    },
    {
      "frame_idx": 1216,
      "timestamp": 20.2776,
      "right_knee_angle": 129.17,
      "left_knee_angle": 92.33,
      "right_hip_angle": 126.84,
      "left_hip_angle": 78.64
    },
    {
      "frame_idx": 1217,
      "timestamp": 20.2943,
      "right_knee_angle": 126.92,
      "left_knee_angle": 93.31,
      "right_hip_angle": 126.87,
      "left_hip_angle": 78.47
    },
    {
      "frame_idx": 1218,
      "timestamp": 20.311,
      "right_knee_angle": 118.74,
      "left_knee_angle": 93.89,
      "right_hip_angle": 122.91,
      "left_hip_angle": 77.7
    },
    {
      "frame_idx": 1219,
      "timestamp": 20.3277,
      "right_knee_angle": 110.73,
      "left_knee_angle": 94.88,
      "right_hip_angle": 117.87,
      "left_hip_angle": 82.5
    },
    {
      "frame_idx": 1220,
      "timestamp": 20.3443,
      "right_knee_angle": 108.07,
      "left_knee_angle": 103.48,
      "right_hip_angle": 118.36,
      "left_hip_angle": 87.19
    },
    {
      "frame_idx": 1221,
      "timestamp": 20.361,
      "right_knee_angle": 109.43,
      "left_knee_angle": 107.41,
      "right_hip_angle": 126.24,
      "left_hip_angle": 87.86
    },
    {
      "frame_idx": 1222,
      "timestamp": 20.3777,
      "right_knee_angle": 103.16,
      "left_knee_angle": 110.71,
      "right_hip_angle": 121.34,
      "left_hip_angle": 90.0
    },
    {
      "frame_idx": 1223,
      "timestamp": 20.3944,
      "right_knee_angle": null,
      "left_knee_angle": 114.02,
      "right_hip_angle": 71.37,
      "left_hip_angle": 91.67
    },
    {
      "frame_idx": 1224,
      "timestamp": 20.411,
      "right_knee_angle": null,
      "left_knee_angle": 119.43,
      "right_hip_angle": 79.54,
      "left_hip_angle": 94.81
    },
    {
      "frame_idx": 1225,
      "timestamp": 20.4277,
      "right_knee_angle": 89.22,
      "left_knee_angle": 122.58,
      "right_hip_angle": 107.45,
      "left_hip_angle": 93.79
    },
    {
      "frame_idx": 1226,
      "timestamp": 20.4444,
      "right_knee_angle": 85.51,
      "left_knee_angle": 124.88,
      "right_hip_angle": 108.13,
      "left_hip_angle": 98.3
    },
    {
      "frame_idx": 1227,
      "timestamp": 20.4611,
      "right_knee_angle": 83.81,
      "left_knee_angle": 126.57,
      "right_hip_angle": 109.95,
      "left_hip_angle": 100.47
    },
    {
      "frame_idx": 1228,
      "timestamp": 20.4777,
      "right_knee_angle": 85.04,
      "left_knee_angle": 129.25,
      "right_hip_angle": 112.75,
      "left_hip_angle": 101.19
    },
    {
      "frame_idx": 1229,
      "timestamp": 20.4944,
      "right_knee_angle": 84.58,
      "left_knee_angle": 133.76,
      "right_hip_angle": 108.0,
      "left_hip_angle": 104.05
    },
    {
      "frame_idx": 1230,
      "timestamp": 20.5111,
      "right_knee_angle": 82.54,
      "left_knee_angle": 131.81,
      "right_hip_angle": 101.73,
      "left_hip_angle": 106.62
    },
    {
      "frame_idx": 1231,
      "timestamp": 20.5278,
      "right_knee_angle": 79.23,
      "left_knee_angle": 131.91,
      "right_hip_angle": 100.03,
      "left_hip_angle": 106.7
    },
    {
      "frame_idx": 1232,
      "timestamp": 20.5444,
      "right_knee_angle": 77.28,
      "left_knee_angle": 135.85,
      "right_hip_angle": 93.97,
      "left_hip_angle": 110.57
    },
    {
      "frame_idx": 1233,
      "timestamp": 20.5611,
      "right_knee_angle": 82.11,
      "left_knee_angle": 137.17,
      "right_hip_angle": 100.49,
      "left_hip_angle": 113.29
    },
    {
      "frame_idx": 1234,
      "timestamp": 20.5778,
      "right_knee_angle": 84.42,
      "left_knee_angle": 136.02,
      "right_hip_angle": 97.67,
      "left_hip_angle": 112.76
    },
    {
      "frame_idx": 1235,
      "timestamp": 20.5945,
      "right_knee_angle": 81.5,
      "left_knee_angle": 134.88,
      "right_hip_angle": 98.04,
      "left_hip_angle": 111.61
    },
    {
      "frame_idx": 1236,
      "timestamp": 20.6111,
      "right_knee_angle": 74.86,
      "left_knee_angle": 131.67,
      "right_hip_angle": 95.85,
      "left_hip_angle": 111.58
    },
    {
      "frame_idx": 1237,
      "timestamp": 20.6278,
      "right_knee_angle": 89.37,
      "left_knee_angle": 130.47,
      "right_hip_angle": 95.21,
      "left_hip_angle": 108.97
    },
    {
      "frame_idx": 1238,
      "timestamp": 20.6445,
      "right_knee_angle": 93.56,
      "left_knee_angle": 125.73,
      "right_hip_angle": 96.11,
      "left_hip_angle": 107.29
    },
    {
      "frame_idx": 1239,
      "timestamp": 20.6612,
      "right_knee_angle": 95.94,
      "left_knee_angle": 119.98,
      "right_hip_angle": 100.51,
      "left_hip_angle": 105.42
    },
    {
      "frame_idx": 1240,
      "timestamp": 20.6778,
      "right_knee_angle": 94.3,
      "left_knee_angle": 117.71,
      "right_hip_angle": 101.0,
      "left_hip_angle": 106.83
    },
    {
      "frame_idx": 1241,
      "timestamp": 20.6945,
      "right_knee_angle": 93.16,
      "left_knee_angle": 113.25,
      "right_hip_angle": 100.76,
      "left_hip_angle": 106.02
    },
    {
      "frame_idx": 1242,
      "timestamp": 20.7112,
      "right_knee_angle": 95.9,
      "left_knee_angle": 112.66,
      "right_hip_angle": 99.27,
      "left_hip_angle": 102.97
    },
    {
      "frame_idx": 1243,
      "timestamp": 20.7279,
      "right_knee_angle": 93.09,
      "left_knee_angle": 109.58,
      "right_hip_angle": 99.67,
      "left_hip_angle": 103.86
    },
    {
      "frame_idx": 1244,
      "timestamp": 20.7445,
      "right_knee_angle": 98.21,
      "left_knee_angle": 104.96,
      "right_hip_angle": 97.97,
      "left_hip_angle": 100.49
    },
    {
      "frame_idx": 1245,
      "timestamp": 20.7612,
      "right_knee_angle": 106.99,
      "left_knee_angle": 101.54,
      "right_hip_angle": 100.69,
      "left_hip_angle": 99.07
    },
    {
      "frame_idx": 1246,
      "timestamp": 20.7779,
      "right_knee_angle": null,
      "left_knee_angle": 102.19,
      "right_hip_angle": null,
      "left_hip_angle": 98.54
    }
  ],
  "summary": {
    "knee_angles_count": 304,
    "knee_angle_mean": 113.74,
    "knee_angle_std": 21.5,
    "knee_angle_peak": 147.51,
    "peak_angle_method": "peak_mean",
    "optimal_range": [
      145.0,
      155.0
    ],
    "verdict": "optimal",
    "verdict_detail": "Peak knee extension 147.5\u00b0 is within the optimal range (145.0\u2013155.0\u00b0)."
  }
}